autojs_py/__init__.py
autojs_py/capture.py
autojs_py/colors.py
autojs_py/Device.py
autojs_py/key.py
autojs_py/main.py
autojs_py/ocr.py
autojs_py/opearation.py
autojs_py/reconginze.py
autojs_py-0.1.1.dist-info/METADATA
autojs_py-0.1.1.dist-info/WHEEL
autojs_py-0.1.1.dist-info/RECORD
