Metadata-Version: 2.1
Name: autojs-py
Version: 0.1.1
Summary: autojs python version
Author: angleyanalbedo
Author-email: 100198247+angleyanalbedo@users.noreply.github.com
Requires-Python: >=3.12,<4.0
Classifier: Programming Language :: Python :: 3
Classifier: Programming Language :: Python :: 3.12
Requires-Dist: numpy (>=2.2.1,<3.0.0)
Requires-Dist: opencv-python (>=4.10.0.84,<5.0.0.0)
Requires-Dist: pyautogui (>=0.9.54,<0.10.0)
Requires-Dist: pytesseract (>=0.3.13,<0.4.0)
Requires-Dist: pytest (>=8.3.4,<9.0.0)
